pymls/__init__.py
pymls/analysis.py
pymls/backing.py
pymls/solver.py
pymls/interface/__init__.py
pymls/interface/interfaces.py
pymls/interface/interfaces_rigid.py
pymls/interface/utils.py
pymls/layers/__init__.py
pymls/layers/elastic.py
pymls/layers/fluid.py
pymls/layers/layer.py
pymls/layers/pem.py
pymls/layers/screen.py
pymls/layers/utils.py
pymls/utils/__init__.py
pymls/utils/draws_manager.py
pymls/utils/indicators.py
pymls/utils/yaml_loader.py
tests/__init__.py
tests/test_solver.py
pymls-1.8.1.dist-info/LICENSE
pymls-1.8.1.dist-info/METADATA
pymls-1.8.1.dist-info/WHEEL
pymls-1.8.1.dist-info/top_level.txt
pymls-1.8.1.dist-info/RECORD
