Metadata-Version: 2.1
Name: pymls
Version: 1.8.1
Summary: Acoustic multilayer solver in Python
Home-page: https://github.com/cpplanes/pymls
Author: O. Dazel, Mathieu (matael) Gaborit, P. Göransson
Author-email: gaborit@kth.se
License: MIT
Classifier: Programming Language :: Python :: 3
Classifier: Operating System :: OS Independent
License-File: LICENSE
Requires-Dist: numpy>=1.13.1
Requires-Dist: PyYAML>=5.1
Requires-Dist: mediapack>=0.3
